{"Town": "CAPE TOWN", "Suburb": "MONTE VISTA", "Street": "HUISING AVENUE", "Latitude": -33.881806, "Longitude": 18.553256, "ProvinceID": 9, "Province": "Western Cape", "MunicipalityID": 9006, "Municipality": "CPT - City of Cape Town", "WardID": 19100001, "VDNumber": 97140089, "VotingDistrict": "MONTE VISTA PRIMARY SCHOOL", "VDAddress": "MONTE VISTA, HUISING AVENUE, CAPE TOWN", "results": {"1335": {"ElectoralEventID": 1335, "ElectoralEvent": "2024 PROVINCIAL ELECTION", "ProvinceID": 9, "Province": "Western Cape", "MunicipalityID": 9006, "Municipality": "CPT - City of Cape Town", "WardID": 19100001, "VDNumber": 97140089, "RegisteredVoters": 3690, "SpoiltVotes": 2, "Section24AVotes": 0, "SpecialVotes": 131, "PercVoterTurnout": 73.63, "TotalVotesCast": 2717, "TotalValidVotes": 2715, "VDCount": 1, "VDWithResultsCaptured": 1, "bResultsComplete": true, "PartyBallotResults": [{"ID": 52, "Name": "DEMOCRATIC ALLIANCE", "ValidVotes": 2409, "PercOfVotes": 88.729281768, "PartyAbbr": "DA", "BallotTypeID": 2, "BallotType": "Provincial", "bIsIndependent": false}, {"ID": 4, "Name": "VRYHEIDSFRONT PLUS", "ValidVotes": 58, "PercOfVotes": 2.136279926, "PartyAbbr": "VF PLUS", "BallotTypeID": 2, "BallotType": "Provincial", "bIsIndependent": false}, {"ID": 7, "Name": "AFRICAN NATIONAL CONGRESS", "ValidVotes": 43, "PercOfVotes": 1.583793738, "PartyAbbr": "ANC", "BallotTypeID": 2, "BallotType": "Provincial", "bIsIndependent": false}, {"ID": 18, "Name": "AFRICAN CHRISTIAN DEMOCRATIC PARTY", "ValidVotes": 37, "PercOfVotes": 1.362799263, "PartyAbbr": "ACDP", "BallotTypeID": 2, "BallotType": "Provincial", "bIsIndependent": false}, {"ID": 945, "Name": "ECONOMIC FREEDOM FIGHTERS", "ValidVotes": 31, "PercOfVotes": 1.141804788, "PartyAbbr": "EFF", "BallotTypeID": 2, "BallotType": "Provincial", "bIsIndependent": false}, {"ID": 447, "Name": "AL JAMA-AH", "ValidVotes": 25, "PercOfVotes": 0.920810313, "PartyAbbr": "ALJAMA", "BallotTypeID": 2, "BallotType": "Provincial", "bIsIndependent": false}, {"ID": 957, "Name": "PATRIOTIC ALLIANCE", "ValidVotes": 23, "PercOfVotes": 0.847145488, "PartyAbbr": "PA", "BallotTypeID": 2, "BallotType": "Provincial", "bIsIndependent": false}, {"ID": 1799, "Name": "REFERENDUM PARTY", "ValidVotes": 22, "PercOfVotes": 0.810313076, "PartyAbbr": "RP", "BallotTypeID": 2, "BallotType": "Provincial", "bIsIndependent": false}, {"ID": 1368, "Name": "GOOD", "ValidVotes": 14, "PercOfVotes": 0.515653775, "PartyAbbr": "GOOD", "BallotTypeID": 2, "BallotType": "Provincial", "bIsIndependent": false}, {"ID": 1492, "Name": "NATIONAL COLOURED CONGRESS", "ValidVotes": 14, "PercOfVotes": 0.515653775, "PartyAbbr": "CCC", "BallotTypeID": 2, "BallotType": "Provincial", "bIsIndependent": false}, {"ID": 1711, "Name": "BUILD ONE SOUTH AFRICA WITH MMUSI MAIMANE", "ValidVotes": 10, "PercOfVotes": 0.368324125, "PartyAbbr": "BOSA", "BallotTypeID": 2, "BallotType": "Provincial", "bIsIndependent": false}, {"ID": 1067, "Name": "ALLIED MOVEMENT FOR CHANGE", "ValidVotes": 7, "PercOfVotes": 0.257826888, "PartyAbbr": "AM4C", "BallotTypeID": 2, "BallotType": "Provincial", "bIsIndependent": false}, {"ID": 1511, "Name": "ACTIONSA", "ValidVotes": 5, "PercOfVotes": 0.184162063, "PartyAbbr": "ACTIONSA", "BallotTypeID": 2, "BallotType": "Provincial", "bIsIndependent": false}, {"ID": 8, "Name": "PAN AFRICANIST CONGRESS OF AZANIA", "ValidVotes": 4, "PercOfVotes": 0.14732965, "PartyAbbr": "PAC", "BallotTypeID": 2, "BallotType": "Provincial", "bIsIndependent": false}, {"ID": 1748, "Name": "UMKHONTO WESIZWE ", "ValidVotes": 4, "PercOfVotes": 0.14732965, "PartyAbbr": "M.K.", "BallotTypeID": 2, "BallotType": "Provincial", "bIsIndependent": false}, {"ID": 1074, "Name": "AZANIA PEACEFUL REVOLUTION", "ValidVotes": 3, "PercOfVotes": 0.110497238, "PartyAbbr": "AZANIA", "BallotTypeID": 2, "BallotType": "Provincial", "bIsIndependent": false}, {"ID": 1755, "Name": "RISE MZANSI ", "ValidVotes": 3, "PercOfVotes": 0.110497238, "PartyAbbr": "RISE ", "BallotTypeID": 2, "BallotType": "Provincial", "bIsIndependent": false}, {"ID": 499, "Name": "CONGRESS  OF THE PEOPLE", "ValidVotes": 2, "PercOfVotes": 0.073664825, "PartyAbbr": "COPE", "BallotTypeID": 2, "BallotType": "Provincial", "bIsIndependent": false}, {"ID": 6, "Name": "UNITED DEMOCRATIC MOVEMENT", "ValidVotes": 1, "PercOfVotes": 0.036832413, "PartyAbbr": "UDM", "BallotTypeID": 2, "BallotType": "Provincial", "bIsIndependent": false}, {"ID": 1523, "Name": "AFRICA RESTORATION ALLIANCE", "ValidVotes": 0, "PercOfVotes": 0.0, "PartyAbbr": "ARA", "BallotTypeID": 2, "BallotType": "Provincial", "bIsIndependent": false}, {"ID": 330, "Name": "AFRICAN INDEPENDENT CONGRESS", "ValidVotes": 0, "PercOfVotes": 0.0, "PartyAbbr": "AIC", "BallotTypeID": 2, "BallotType": "Provincial", "bIsIndependent": false}, {"ID": 1318, "Name": "AFRICAN TRANSFORMATION MOVEMENT", "ValidVotes": 0, "PercOfVotes": 0.0, "PartyAbbr": "ATM", "BallotTypeID": 2, "BallotType": "Provincial", "bIsIndependent": false}, {"ID": 1754, "Name": "ALLIANCE OF CITIZENS FOR CHANGE ", "ValidVotes": 0, "PercOfVotes": 0.0, "PartyAbbr": "A.C.C.", "BallotTypeID": 2, "BallotType": "Provincial", "bIsIndependent": false}, {"ID": 1725, "Name": "ARISE SOUTH AFRICA", "ValidVotes": 0, "PercOfVotes": 0.0, "PartyAbbr": "ASA", "BallotTypeID": 2, "BallotType": "Provincial", "bIsIndependent": false}, {"ID": 3, "Name": "INKATHA FREEDOM PARTY", "ValidVotes": 0, "PercOfVotes": 0.0, "PartyAbbr": "IFP", "BallotTypeID": 2, "BallotType": "Provincial", "bIsIndependent": false}, {"ID": 1352, "Name": "LAND PARTY", "ValidVotes": 0, "PercOfVotes": 0.0, "PartyAbbr": "LAND", "BallotTypeID": 2, "BallotType": "Provincial", "bIsIndependent": false}, {"ID": 1758, "Name": "OPERATION DUDULA ", "ValidVotes": 0, "PercOfVotes": 0.0, "PartyAbbr": "O.D", "BallotTypeID": 2, "BallotType": "Provincial", "bIsIndependent": false}, {"ID": 1335, "Name": "PEOPLE'S MOVEMENT FOR CHANGE", "ValidVotes": 0, "PercOfVotes": 0.0, "PartyAbbr": "PMC", "BallotTypeID": 2, "BallotType": "Provincial", "bIsIndependent": false}, {"ID": 1004, "Name": "SIZWE UMMAH NATION", "ValidVotes": 0, "PercOfVotes": 0.0, "PartyAbbr": "SUN", "BallotTypeID": 2, "BallotType": "Provincial", "bIsIndependent": false}]}, "1334": {"ElectoralEventID": 1334, "ElectoralEvent": "2024 NATIONAL ELECTION", "ProvinceID": 9, "Province": "Western Cape", "MunicipalityID": 9006, "Municipality": "CPT - City of Cape Town", "WardID": 19100001, "VDNumber": 97140089, "RegisteredVoters": 3690, "SpoiltVotes": 6, "Section24AVotes": 0, "SpecialVotes": 131, "PercVoterTurnout": 77.89, "TotalVotesCast": 2874, "TotalValidVotes": 2868, "VDCount": 1, "VDWithResultsCaptured": 1, "bResultsComplete": true, "PartyBallotResults": [{"ID": 52, "Name": "DEMOCRATIC ALLIANCE", "ValidVotes": 2542, "PercOfVotes": 88.633193863, "PartyAbbr": "DA", "BallotTypeID": 1, "BallotType": "National", "bIsIndependent": false}, {"ID": 52, "Name": "DEMOCRATIC ALLIANCE", "ValidVotes": 1765, "PercOfVotes": 82.631086142, "PartyAbbr": "DA", "BallotTypeID": 3, "BallotType": "Regional", "bIsIndependent": false}, {"ID": 7, "Name": "AFRICAN NATIONAL CONGRESS", "ValidVotes": 71, "PercOfVotes": 2.475592748, "PartyAbbr": "ANC", "BallotTypeID": 1, "BallotType": "National", "bIsIndependent": false}, {"ID": 4, "Name": "VRYHEIDSFRONT PLUS", "ValidVotes": 71, "PercOfVotes": 3.323970037, "PartyAbbr": "VF PLUS", "BallotTypeID": 3, "BallotType": "Regional", "bIsIndependent": false}, {"ID": 18, "Name": "AFRICAN CHRISTIAN DEMOCRATIC PARTY", "ValidVotes": 65, "PercOfVotes": 3.043071161, "PartyAbbr": "ACDP", "BallotTypeID": 3, "BallotType": "Regional", "bIsIndependent": false}, {"ID": 18, "Name": "AFRICAN CHRISTIAN DEMOCRATIC PARTY", "ValidVotes": 63, "PercOfVotes": 2.19665272, "PartyAbbr": "ACDP", "BallotTypeID": 1, "BallotType": "National", "bIsIndependent": false}, {"ID": 945, "Name": "ECONOMIC FREEDOM FIGHTERS", "ValidVotes": 47, "PercOfVotes": 1.638772664, "PartyAbbr": "EFF", "BallotTypeID": 1, "BallotType": "National", "bIsIndependent": false}, {"ID": 7, "Name": "AFRICAN NATIONAL CONGRESS", "ValidVotes": 42, "PercOfVotes": 1.966292135, "PartyAbbr": "ANC", "BallotTypeID": 3, "BallotType": "Regional", "bIsIndependent": false}, {"ID": 945, "Name": "ECONOMIC FREEDOM FIGHTERS", "ValidVotes": 36, "PercOfVotes": 1.685393258, "PartyAbbr": "EFF", "BallotTypeID": 3, "BallotType": "Regional", "bIsIndependent": false}, {"ID": 447, "Name": "AL JAMA-AH", "ValidVotes": 24, "PercOfVotes": 1.123595506, "PartyAbbr": "ALJAMA", "BallotTypeID": 3, "BallotType": "Regional", "bIsIndependent": false}, {"ID": 4, "Name": "VRYHEIDSFRONT PLUS", "ValidVotes": 24, "PercOfVotes": 0.836820084, "PartyAbbr": "VF PLUS", "BallotTypeID": 1, "BallotType": "National", "bIsIndependent": false}, {"ID": 957, "Name": "PATRIOTIC ALLIANCE", "ValidVotes": 23, "PercOfVotes": 0.80195258, "PartyAbbr": "PA", "BallotTypeID": 1, "BallotType": "National", "bIsIndependent": false}, {"ID": 957, "Name": "PATRIOTIC ALLIANCE", "ValidVotes": 22, "PercOfVotes": 1.029962547, "PartyAbbr": "PA", "BallotTypeID": 3, "BallotType": "Regional", "bIsIndependent": false}, {"ID": 1368, "Name": "GOOD", "ValidVotes": 18, "PercOfVotes": 0.842696629, "PartyAbbr": "GOOD", "BallotTypeID": 3, "BallotType": "Regional", "bIsIndependent": false}, {"ID": 1644, "Name": "UNITED INDEPENDENT MOVEMENT", "ValidVotes": 17, "PercOfVotes": 0.79588015, "PartyAbbr": "UIM", "BallotTypeID": 3, "BallotType": "Regional", "bIsIndependent": false}, {"ID": 1799, "Name": "REFERENDUM PARTY", "ValidVotes": 16, "PercOfVotes": 0.74906367, "PartyAbbr": "RP", "BallotTypeID": 3, "BallotType": "Regional", "bIsIndependent": false}, {"ID": 1368, "Name": "GOOD", "ValidVotes": 14, "PercOfVotes": 0.488145049, "PartyAbbr": "GOOD", "BallotTypeID": 1, "BallotType": "National", "bIsIndependent": false}, {"ID": 1711, "Name": "BUILD ONE SOUTH AFRICA WITH MMUSI MAIMANE", "ValidVotes": 13, "PercOfVotes": 0.608614232, "PartyAbbr": "BOSA", "BallotTypeID": 3, "BallotType": "Regional", "bIsIndependent": false}, {"ID": 1755, "Name": "RISE MZANSI ", "ValidVotes": 12, "PercOfVotes": 0.418410042, "PartyAbbr": "RISE ", "BallotTypeID": 1, "BallotType": "National", "bIsIndependent": false}, {"ID": 1711, "Name": "BUILD ONE SOUTH AFRICA WITH MMUSI MAIMANE", "ValidVotes": 11, "PercOfVotes": 0.383542538, "PartyAbbr": "BOSA", "BallotTypeID": 1, "BallotType": "National", "bIsIndependent": false}, {"ID": 1492, "Name": "NATIONAL COLOURED CONGRESS", "ValidVotes": 10, "PercOfVotes": 0.468164794, "PartyAbbr": "CCC", "BallotTypeID": 3, "BallotType": "Regional", "bIsIndependent": false}, {"ID": 1801, "Name": "#HOPE4SA", "ValidVotes": 8, "PercOfVotes": 0.374531835, "PartyAbbr": "#HOPE4SA", "BallotTypeID": 3, "BallotType": "Regional", "bIsIndependent": false}, {"ID": 1511, "Name": "ACTIONSA", "ValidVotes": 8, "PercOfVotes": 0.278940028, "PartyAbbr": "ACTIONSA", "BallotTypeID": 1, "BallotType": "National", "bIsIndependent": false}, {"ID": 1492, "Name": "NATIONAL COLOURED CONGRESS", "ValidVotes": 8, "PercOfVotes": 0.278940028, "PartyAbbr": "CCC", "BallotTypeID": 1, "BallotType": "National", "bIsIndependent": false}, {"ID": 1748, "Name": "UMKHONTO WESIZWE ", "ValidVotes": 8, "PercOfVotes": 0.278940028, "PartyAbbr": "M.K.", "BallotTypeID": 1, "BallotType": "National", "bIsIndependent": false}, {"ID": 1801, "Name": "#HOPE4SA", "ValidVotes": 7, "PercOfVotes": 0.244072524, "PartyAbbr": "#HOPE4SA", "BallotTypeID": 1, "BallotType": "National", "bIsIndependent": false}, {"ID": 1067, "Name": "ALLIED MOVEMENT FOR CHANGE", "ValidVotes": 7, "PercOfVotes": 0.244072524, "PartyAbbr": "AM4C", "BallotTypeID": 1, "BallotType": "National", "bIsIndependent": false}, {"ID": 1067, "Name": "ALLIED MOVEMENT FOR CHANGE", "ValidVotes": 7, "PercOfVotes": 0.327715356, "PartyAbbr": "AM4C", "BallotTypeID": 3, "BallotType": "Regional", "bIsIndependent": false}, {"ID": 1362, "Name": "ORGANIC HUMANITY MOVEMENT", "ValidVotes": 6, "PercOfVotes": 0.280898876, "PartyAbbr": "OHM", "BallotTypeID": 3, "BallotType": "Regional", "bIsIndependent": false}, {"ID": 1799, "Name": "REFERENDUM PARTY", "ValidVotes": 6, "PercOfVotes": 0.209205021, "PartyAbbr": "RP", "BallotTypeID": 1, "BallotType": "National", "bIsIndependent": false}, {"ID": 1511, "Name": "ACTIONSA", "ValidVotes": 5, "PercOfVotes": 0.234082397, "PartyAbbr": "ACTIONSA", "BallotTypeID": 3, "BallotType": "Regional", "bIsIndependent": false}, {"ID": 447, "Name": "AL JAMA-AH", "ValidVotes": 4, "PercOfVotes": 0.139470014, "PartyAbbr": "ALJAMA", "BallotTypeID": 1, "BallotType": "National", "bIsIndependent": false}, {"ID": 1362, "Name": "ORGANIC HUMANITY MOVEMENT", "ValidVotes": 4, "PercOfVotes": 0.139470014, "PartyAbbr": "OHM", "BallotTypeID": 1, "BallotType": "National", "bIsIndependent": false}, {"ID": 1748, "Name": "UMKHONTO WESIZWE ", "ValidVotes": 4, "PercOfVotes": 0.187265918, "PartyAbbr": "M.K.", "BallotTypeID": 3, "BallotType": "Regional", "bIsIndependent": false}, {"ID": 1644, "Name": "UNITED INDEPENDENT MOVEMENT", "ValidVotes": 4, "PercOfVotes": 0.139470014, "PartyAbbr": "UIM", "BallotTypeID": 1, "BallotType": "National", "bIsIndependent": false}, {"ID": 1354, "Name": "FREE DEMOCRATS", "ValidVotes": 2, "PercOfVotes": 0.069735007, "PartyAbbr": "FREE DEMS", "BallotTypeID": 1, "BallotType": "National", "bIsIndependent": false}, {"ID": 6, "Name": "UNITED DEMOCRATIC MOVEMENT", "ValidVotes": 2, "PercOfVotes": 0.093632959, "PartyAbbr": "UDM", "BallotTypeID": 3, "BallotType": "Regional", "bIsIndependent": false}, {"ID": 17, "Name": "AZANIAN PEOPLE'S ORGANISATION", "ValidVotes": 1, "PercOfVotes": 0.034867503, "PartyAbbr": "AZAPO", "BallotTypeID": 1, "BallotType": "National", "bIsIndependent": false}, {"ID": 17, "Name": "AZANIAN PEOPLE'S ORGANISATION", "ValidVotes": 1, "PercOfVotes": 0.046816479, "PartyAbbr": "AZAPO", "BallotTypeID": 3, "BallotType": "Regional", "bIsIndependent": false}, {"ID": 499, "Name": "CONGRESS  OF THE PEOPLE", "ValidVotes": 1, "PercOfVotes": 0.034867503, "PartyAbbr": "COPE", "BallotTypeID": 1, "BallotType": "National", "bIsIndependent": false}, {"ID": 499, "Name": "CONGRESS  OF THE PEOPLE", "ValidVotes": 1, "PercOfVotes": 0.046816479, "PartyAbbr": "COPE", "BallotTypeID": 3, "BallotType": "Regional", "bIsIndependent": false}, {"ID": 1354, "Name": "FREE DEMOCRATS", "ValidVotes": 1, "PercOfVotes": 0.046816479, "PartyAbbr": "FREE DEMS", "BallotTypeID": 3, "BallotType": "Regional", "bIsIndependent": false}, {"ID": 3, "Name": "INKATHA FREEDOM PARTY", "ValidVotes": 1, "PercOfVotes": 0.046816479, "PartyAbbr": "IFP", "BallotTypeID": 3, "BallotType": "Regional", "bIsIndependent": false}, {"ID": 8, "Name": "PAN AFRICANIST CONGRESS OF AZANIA", "ValidVotes": 1, "PercOfVotes": 0.046816479, "PartyAbbr": "PAC", "BallotTypeID": 3, "BallotType": "Regional", "bIsIndependent": false}, {"ID": 6, "Name": "UNITED DEMOCRATIC MOVEMENT", "ValidVotes": 1, "PercOfVotes": 0.034867503, "PartyAbbr": "UDM", "BallotTypeID": 1, "BallotType": "National", "bIsIndependent": false}, {"ID": 1488, "Name": "ABANTU BATHO CONGRESS", "ValidVotes": 0, "PercOfVotes": 0.0, "PartyAbbr": "ABC", "BallotTypeID": 1, "BallotType": "National", "bIsIndependent": false}, {"ID": 1531, "Name": "ABLE LEADERSHIP", "ValidVotes": 0, "PercOfVotes": 0.0, "PartyAbbr": "AL", "BallotTypeID": 1, "BallotType": "National", "bIsIndependent": false}, {"ID": 0, "Name": "ACHMAT ZACKIE - 583999", "ValidVotes": 0, "PercOfVotes": 0.0, "PartyAbbr": "IND", "BallotTypeID": 3, "BallotType": "Regional", "bIsIndependent": true}, {"ID": 1728, "Name": "ACTION ALLIANCE DEVELOPMENT PARTY", "ValidVotes": 0, "PercOfVotes": 0.0, "PartyAbbr": "AADP", "BallotTypeID": 1, "BallotType": "National", "bIsIndependent": false}, {"ID": 1763, "Name": "AFRICA AFRICANS RECLAIM ", "ValidVotes": 0, "PercOfVotes": 0.0, "PartyAbbr": "AAR", "BallotTypeID": 1, "BallotType": "National", "bIsIndependent": false}, {"ID": 1523, "Name": "AFRICA RESTORATION ALLIANCE", "ValidVotes": 0, "PercOfVotes": 0.0, "PartyAbbr": "ARA", "BallotTypeID": 1, "BallotType": "National", "bIsIndependent": false}, {"ID": 1523, "Name": "AFRICA RESTORATION ALLIANCE", "ValidVotes": 0, "PercOfVotes": 0.0, "PartyAbbr": "ARA", "BallotTypeID": 3, "BallotType": "Regional", "bIsIndependent": false}, {"ID": 1740, "Name": "AFRICAN CONGRESS FOR TRANSFORMATION", "ValidVotes": 0, "PercOfVotes": 0.0, "PartyAbbr": "ACT", "BallotTypeID": 1, "BallotType": "National", "bIsIndependent": false}, {"ID": 1740, "Name": "AFRICAN CONGRESS FOR TRANSFORMATION", "ValidVotes": 0, "PercOfVotes": 0.0, "PartyAbbr": "ACT", "BallotTypeID": 3, "BallotType": "Regional", "bIsIndependent": false}, {"ID": 1370, "Name": "AFRICAN CONTENT MOVEMENT", "ValidVotes": 0, "PercOfVotes": 0.0, "PartyAbbr": "ACM", "BallotTypeID": 1, "BallotType": "National", "bIsIndependent": false}, {"ID": 1544, "Name": "AFRICAN HEART CONGRESS", "ValidVotes": 0, "PercOfVotes": 0.0, "PartyAbbr": "AHC", "BallotTypeID": 1, "BallotType": "National", "bIsIndependent": false}, {"ID": 330, "Name": "AFRICAN INDEPENDENT CONGRESS", "ValidVotes": 0, "PercOfVotes": 0.0, "PartyAbbr": "AIC", "BallotTypeID": 1, "BallotType": "National", "bIsIndependent": false}, {"ID": 1775, "Name": "AFRICAN MOVEMENT CONGRESS", "ValidVotes": 0, "PercOfVotes": 0.0, "PartyAbbr": "NO_ABBR", "BallotTypeID": 1, "BallotType": "National", "bIsIndependent": false}, {"ID": 450, "Name": "AFRICAN PEOPLE'S CONVENTION", "ValidVotes": 0, "PercOfVotes": 0.0, "PartyAbbr": "APC", "BallotTypeID": 1, "BallotType": "National", "bIsIndependent": false}, {"ID": 450, "Name": "AFRICAN PEOPLE'S CONVENTION", "ValidVotes": 0, "PercOfVotes": 0.0, "PartyAbbr": "APC", "BallotTypeID": 3, "BallotType": "Regional", "bIsIndependent": false}, {"ID": 1528, "Name": "AFRICAN PEOPLE'S MOVEMENT", "ValidVotes": 0, "PercOfVotes": 0.0, "PartyAbbr": "APEMO", "BallotTypeID": 1, "BallotType": "National", "bIsIndependent": false}, {"ID": 1318, "Name": "AFRICAN TRANSFORMATION MOVEMENT", "ValidVotes": 0, "PercOfVotes": 0.0, "PartyAbbr": "ATM", "BallotTypeID": 1, "BallotType": "National", "bIsIndependent": false}, {"ID": 1318, "Name": "AFRICAN TRANSFORMATION MOVEMENT", "ValidVotes": 0, "PercOfVotes": 0.0, "PartyAbbr": "ATM", "BallotTypeID": 3, "BallotType": "Regional", "bIsIndependent": false}, {"ID": 1749, "Name": "ALL CITIZENS PARTY ", "ValidVotes": 0, "PercOfVotes": 0.0, "PartyAbbr": "ACP ", "BallotTypeID": 1, "BallotType": "National", "bIsIndependent": false}, {"ID": 1754, "Name": "ALLIANCE OF CITIZENS FOR CHANGE ", "ValidVotes": 0, "PercOfVotes": 0.0, "PartyAbbr": "A.C.C.", "BallotTypeID": 1, "BallotType": "National", "bIsIndependent": false}, {"ID": 1754, "Name": "ALLIANCE OF CITIZENS FOR CHANGE ", "ValidVotes": 0, "PercOfVotes": 0.0, "PartyAbbr": "A.C.C.", "BallotTypeID": 3, "BallotType": "Regional", "bIsIndependent": false}, {"ID": 1742, "Name": "CITIZANS", "ValidVotes": 0, "PercOfVotes": 0.0, "PartyAbbr": "CITIZANS", "BallotTypeID": 1, "BallotType": "National", "bIsIndependent": false}, {"ID": 1742, "Name": "CITIZANS", "ValidVotes": 0, "PercOfVotes": 0.0, "PartyAbbr": "CITIZANS", "BallotTypeID": 3, "BallotType": "Regional", "bIsIndependent": false}, {"ID": 466, "Name": "CONSERVATIVES IN ACTION", "ValidVotes": 0, "PercOfVotes": 0.0, "PartyAbbr": "CIASA", "BallotTypeID": 1, "BallotType": "National", "bIsIndependent": false}, {"ID": 1036, "Name": "DEMOCRATIC LIBERAL CONGRESS", "ValidVotes": 0, "PercOfVotes": 0.0, "PartyAbbr": "DLC", "BallotTypeID": 1, "BallotType": "National", "bIsIndependent": false}, {"ID": 1790, "Name": "ECONOMIC LIBERATORS FORUM SOUTH AFRICA", "ValidVotes": 0, "PercOfVotes": 0.0, "PartyAbbr": "ELF-SA", "BallotTypeID": 1, "BallotType": "National", "bIsIndependent": false}, {"ID": 1790, "Name": "ECONOMIC LIBERATORS FORUM SOUTH AFRICA", "ValidVotes": 0, "PercOfVotes": 0.0, "PartyAbbr": "ELF-SA", "BallotTypeID": 3, "BallotType": "Regional", "bIsIndependent": false}, {"ID": 1016, "Name": "FORUM 4 SERVICE DELIVERY", "ValidVotes": 0, "PercOfVotes": 0.0, "PartyAbbr": "F4SD", "BallotTypeID": 1, "BallotType": "National", "bIsIndependent": false}, {"ID": 3, "Name": "INKATHA FREEDOM PARTY", "ValidVotes": 0, "PercOfVotes": 0.0, "PartyAbbr": "IFP", "BallotTypeID": 1, "BallotType": "National", "bIsIndependent": false}, {"ID": 591, "Name": "NATIONAL FREEDOM PARTY", "ValidVotes": 0, "PercOfVotes": 0.0, "PartyAbbr": "NFP", "BallotTypeID": 1, "BallotType": "National", "bIsIndependent": false}, {"ID": 1744, "Name": "NORTHERN CAPE COMMUNITIES MOVEMENT", "ValidVotes": 0, "PercOfVotes": 0.0, "PartyAbbr": "NCCM", "BallotTypeID": 1, "BallotType": "National", "bIsIndependent": false}, {"ID": 8, "Name": "PAN AFRICANIST CONGRESS OF AZANIA", "ValidVotes": 0, "PercOfVotes": 0.0, "PartyAbbr": "PAC", "BallotTypeID": 1, "BallotType": "National", "bIsIndependent": false}, {"ID": 1335, "Name": "PEOPLE'S MOVEMENT FOR CHANGE", "ValidVotes": 0, "PercOfVotes": 0.0, "PartyAbbr": "PMC", "BallotTypeID": 1, "BallotType": "National", "bIsIndependent": false}, {"ID": 1335, "Name": "PEOPLE'S MOVEMENT FOR CHANGE", "ValidVotes": 0, "PercOfVotes": 0.0, "PartyAbbr": "PMC", "BallotTypeID": 3, "BallotType": "Regional", "bIsIndependent": false}, {"ID": 1755, "Name": "RISE MZANSI ", "ValidVotes": 0, "PercOfVotes": 0.0, "PartyAbbr": "RISE ", "BallotTypeID": 3, "BallotType": "Regional", "bIsIndependent": false}, {"ID": 1004, "Name": "SIZWE UMMAH NATION", "ValidVotes": 0, "PercOfVotes": 0.0, "PartyAbbr": "SUN", "BallotTypeID": 1, "BallotType": "National", "bIsIndependent": false}, {"ID": 1004, "Name": "SIZWE UMMAH NATION", "ValidVotes": 0, "PercOfVotes": 0.0, "PartyAbbr": "SUN", "BallotTypeID": 3, "BallotType": "Regional", "bIsIndependent": false}, {"ID": 1785, "Name": "SOUTH AFRICAN RAINBOW ALLIANCE ", "ValidVotes": 0, "PercOfVotes": 0.0, "PartyAbbr": "SARA", "BallotTypeID": 1, "BallotType": "National", "bIsIndependent": false}, {"ID": 1785, "Name": "SOUTH AFRICAN RAINBOW ALLIANCE ", "ValidVotes": 0, "PercOfVotes": 0.0, "PartyAbbr": "SARA", "BallotTypeID": 3, "BallotType": "Regional", "bIsIndependent": false}, {"ID": 1623, "Name": "SOUTH AFRICAN ROYAL KINGDOMS ORGANIZATION", "ValidVotes": 0, "PercOfVotes": 0.0, "PartyAbbr": "SARKO", "BallotTypeID": 1, "BallotType": "National", "bIsIndependent": false}, {"ID": 1707, "Name": "UNITED AFRICANS TRANSFORMATION", "ValidVotes": 0, "PercOfVotes": 0.0, "PartyAbbr": "UAT", "BallotTypeID": 1, "BallotType": "National", "bIsIndependent": false}, {"ID": 1729, "Name": "XILUVA", "ValidVotes": 0, "PercOfVotes": 0.0, "PartyAbbr": "XILUVA", "BallotTypeID": 1, "BallotType": "National", "bIsIndependent": false}]}}}